etabar/ETA.py
etabar/__init__.py
etabar-0.0.2.dist-info/LICENSE
etabar-0.0.2.dist-info/METADATA
etabar-0.0.2.dist-info/WHEEL
etabar-0.0.2.dist-info/top_level.txt
etabar-0.0.2.dist-info/RECORD
