Metadata-Version: 2.1
Name: etabar
Version: 0.0.2
Summary: A simple library to display an eta bar
Home-page: https://github.com/mayank8318/ETABar
Author: Mayank Vaidya
Author-email: mayank8318@gmail.com
License: MIT
Keywords: etabar progressbar bar python package mayank8318
Platform: UNKNOWN
Classifier: Programming Language :: Python :: 3
Classifier: License :: OSI Approved :: MIT License
Classifier: Operating System :: OS Independent
